ekogram/__init__.py
ekogram/ekogram.py
ekogram-3.1.dist-info/licenses/LICENSE
ekogram-3.1.dist-info/METADATA
ekogram-3.1.dist-info/WHEEL
ekogram-3.1.dist-info/top_level.txt
ekogram-3.1.dist-info/RECORD
