Metadata-Version: 2.4
Name: ekogram
Version: 3.1
Summary: Lightweight library for working with Telegram Bot Api + Generate Images, Audio and Text
Home-page: https://github.com/SiriRSST/Ekogram
Author: Siri-Team
Author-email: siriteamrs@gmail.com
License: MIT
Project-URL: Source, https://github.com/SiriRSST/Ekogram
Keywords: telebot,bot,gram,pytelegrambotapi,telegram,ekogram,aiogram,gpt,freegpt,openai,ai
Classifier: Programming Language :: Python :: 3
Classifier: License :: OSI Approved :: MIT License
Classifier: Operating System :: OS Independent
Requires-Python: >=3.7
License-File: LICENSE
Requires-Dist: requests
Requires-Dist: bs4
Dynamic: author
Dynamic: author-email
Dynamic: classifier
Dynamic: description
Dynamic: description-content-type
Dynamic: home-page
Dynamic: keywords
Dynamic: license
Dynamic: license-file
Dynamic: project-url
Dynamic: requires-dist
Dynamic: requires-python
Dynamic: summary
